LICENSE
MANIFEST.in
README.md
pyproject.toml
bib/refs.bib
css/highlight.css
css/main.css
js/mathjax-config.js
pymdpages/__init__.py
pymdpages/pymdpages.py
pymdpages.egg-info/PKG-INFO
pymdpages.egg-info/SOURCES.txt
pymdpages.egg-info/dependency_links.txt
pymdpages.egg-info/entry_points.txt
pymdpages.egg-info/requires.txt
pymdpages.egg-info/top_level.txt
pymdpages/mdx_bib/mdx_bib.py
pymdpages/mdx_bib/setup.py
template/head.html
template/tail.html