Metadata-Version: 2.1
Name: pymdpages
Version: 0.0.1.post1
Summary: pymdpages: a minimalistic python-markdown static academic pages generator
Author-email: Renato Lui Geh <renatogeh@gmail.com>
License: MIT
Project-URL: Repository, https://github.com/RenatoGeh/pymdpages
Project-URL: Issues, https://github.com/RenatoGeh/pymdpages/issues
Classifier: Programming Language :: Python :: 3
Classifier: License :: OSI Approved :: MIT License
Classifier: Operating System :: POSIX :: Linux
Classifier: Development Status :: 3 - Alpha
Classifier: Environment :: Console
Requires-Python: >=3.10
License-File: LICENSE
